Metadata-Version: 2.1
Name: datafetch
Version: 0.0.2
Summary: Tools for fetching data, and providing ready-to-use https://prefect.io flows
Home-page: https://github.com/steph-ben/datafetch
Author: steph-ben
Author-email: stephane.benchimol@gmail.com
License: UNKNOWN
Platform: UNKNOWN
Classifier: Programming Language :: Python :: 3
Requires-Dist: boto3 (==1.16.36)
Requires-Dist: prefect[github] (==0.14.6)
Requires-Dist: pydantic (==1.7.3)
Requires-Dist: peewee (==3.14.0)
Requires-Dist: cdsapi (==0.5.1)
